pycloudflare/__init__.py
pycloudflare/cloudflare.py
pycloudflare/request.py
pycloudflaresdk-0.0.1.dist-info/METADATA
pycloudflaresdk-0.0.1.dist-info/WHEEL
pycloudflaresdk-0.0.1.dist-info/top_level.txt
pycloudflaresdk-0.0.1.dist-info/RECORD
