Metadata-Version: 2.1
Name: pycloudflaresdk
Version: 0.0.1
Summary: CLOUDFLARE SDK package
Home-page: https://github.com/Maliaotw/pycloudflare.git
Author: Maliao
Author-email: maliaotw@gmail.com
License: UNKNOWN
Platform: UNKNOWN
Classifier: Programming Language :: Python :: 3
Classifier: License :: OSI Approved :: MIT License
Classifier: Operating System :: OS Independent
Requires-Python: >=3.6
Requires-Dist: requests (>=2.12.3)
